azusa/__init__.py
azusa/__main__.py
azusa/curve_probabilities.py
azusa/mana_producers.py
azusa/parse.py
azusa/util.py
azusa-0.1.5.dist-info/LICENSE
azusa-0.1.5.dist-info/METADATA
azusa-0.1.5.dist-info/WHEEL
azusa-0.1.5.dist-info/top_level.txt
azusa-0.1.5.dist-info/RECORD
