Metadata-Version: 2.1
Name: azusa
Version: 0.1.5
Summary: Probability estimator for being on curve in mtg
Home-page: https://github.com/ihowell/azusa
Author: Ian Howell
License: UNKNOWN
Project-URL: Bug Reports, https://github.com/ihowell/azusa/issues
Project-URL: Source, https://github.com/ihowell/azusa/
Keywords: mtg
Platform: UNKNOWN
Classifier: Development Status :: 3 - Alpha
Classifier: Intended Audience :: Developers
Classifier: Topic :: Software Development :: Build Tools
Classifier: License :: OSI Approved :: MIT License
Classifier: Programming Language :: Python :: 3
Classifier: Programming Language :: Python :: 3.7
Classifier: Programming Language :: Python :: 3.8
Classifier: Programming Language :: Python :: 3 :: Only
Requires-Python: >=3.7, <4
Requires-Dist: scrython
Requires-Dist: fire (==0.3.1)
Requires-Dist: numpy
Requires-Dist: requests
Requires-Dist: terminaltables
Requires-Dist: tqdm
Requires-Dist: python-constraint (==1.4.0)
Provides-Extra: tests
Requires-Dist: pytest ; extra == 'tests'
